nile/__init__.py
nile/controllers.py
nile/interfaces.py
samples/__init__.py
samples/videostream/__init__.py
samples/videostream/main.py
samples/videostream/providers.py
tests/__init__.py
tests/unit/__init__.py
tests/unit/commons.py
tests/unit/test_consumer_delegate.py
tests/unit/test_device_controller.py
tests/unit/test_device_fleet_manager.py
nile-0.0.3.dist-info/LICENSE
nile-0.0.3.dist-info/METADATA
nile-0.0.3.dist-info/WHEEL
nile-0.0.3.dist-info/top_level.txt
nile-0.0.3.dist-info/RECORD
